LICENSE
MANIFEST.in
README.md
setup.cfg
setup.py
src/cPrometheus.c
src/cPrometheus.pyx
src/cPrometheus.egg-info/PKG-INFO
src/cPrometheus.egg-info/SOURCES.txt
src/cPrometheus.egg-info/dependency_links.txt
src/cPrometheus.egg-info/requires.txt
src/cPrometheus.egg-info/top_level.txt
tests/__init__.py
tests/test_cPrometheus.py