Metadata-Version: 1.1
Name: cPrometheus
Version: 0.1
Summary: A monkey patch for prometheus_client, using GCC atomics for extra speed on CPython
Home-page: https://github.com/jamespic/cPrometheus
Author: James Pickering
Author-email: james_pic@hotmail.com
License: MIT
Download-URL: https://github.com/jamespic/cPrometheus/archive/0.1.tar.gz
Keywords: monitoring
Platform: UNKNOWN
Classifier: License :: OSI Approved :: MIT License
Classifier: Topic :: System :: Monitoring
